CPSE/Buffers.py
CPSE/Cpse.py
CPSE/CpseFrame.py
CPSE/CpseObject.py
CPSE/__init__.py
Cpse-0.0.1.dist-info/LICENSE
Cpse-0.0.1.dist-info/METADATA
Cpse-0.0.1.dist-info/WHEEL
Cpse-0.0.1.dist-info/top_level.txt
Cpse-0.0.1.dist-info/RECORD
